<annotation>
	<folder>VOC2007</folder>
	<filename>im_fn</filename>
	<source>
		<database>ROMYNY Database</database>
		<annotation>ROMYNY Annotation</annotation>
		<image>Unspecified</image>
	</source>
	<owner>
		<name>Unspecified</name>
	</owner>
	<size>
		<width>512</width>
		<height>512</height>
		<depth>3</depth>
	</size>
	<segmented>0</segmented>
	<object>
		<name>Facebook-Text</name>
		<pose>Unspecified</pose>
		<truncated>1</truncated>
		<difficult>0</difficult>
		<bndbox>
			<xmin>211</xmin>
			<ymin>139</ymin>
			<xmax>355</xmax>
			<ymax>357</ymax>
		</bndbox>
	</object>
</annotation>