<annotation>
	<folder>VOC2007</folder>
	<filename>im_fn</filename>
	<source>
		<database>ROMYNY Database</database>
		<annotation>ROMYNY Annotation</annotation>
		<image>Unspecified</image>
	</source>
	<owner>
		<name>Unspecified</name>
	</owner>
	<size>
		<width>700</width>
		<height>417</height>
		<depth>3</depth>
	</size>
	<segmented>0</segmented>
	<object>
		<name>FC_Barcelona</name>
		<pose>Unspecified</pose>
		<truncated>1</truncated>
		<difficult>0</difficult>
		<bndbox>
			<xmin>255</xmin>
			<ymin>287</ymin>
			<xmax>555</xmax>
			<ymax>405</ymax>
		</bndbox>
	</object>
</annotation>