<annotation>
	<folder>VOC2007</folder>
	<filename>im_fn</filename>
	<source>
		<database>ROMYNY Database</database>
		<annotation>ROMYNY Annotation</annotation>
		<image>Unspecified</image>
	</source>
	<owner>
		<name>Unspecified</name>
	</owner>
	<size>
		<width>800</width>
		<height>532</height>
		<depth>3</depth>
	</size>
	<segmented>0</segmented>
	<object>
		<name>Audi-Text</name>
		<pose>Unspecified</pose>
		<truncated>1</truncated>
		<difficult>0</difficult>
		<bndbox>
			<xmin>483</xmin>
			<ymin>168</ymin>
			<xmax>539</xmax>
			<ymax>213</ymax>
		</bndbox>
	</object>
	<object>
		<name>Audi-Pict</name>
		<pose>Unspecified</pose>
		<truncated>1</truncated>
		<difficult>0</difficult>
		<bndbox>
			<xmin>390</xmin>
			<ymin>117</ymin>
			<xmax>481</xmax>
			<ymax>189</ymax>
		</bndbox>
	</object>
	<object>
		<name>Audi-Pict</name>
		<pose>Unspecified</pose>
		<truncated>1</truncated>
		<difficult>0</difficult>
		<bndbox>
			<xmin>31</xmin>
			<ymin>250</ymin>
			<xmax>68</xmax>
			<ymax>284</ymax>
		</bndbox>
	</object>
	<object>
		<name>Audi-Text</name>
		<pose>Unspecified</pose>
		<truncated>1</truncated>
		<difficult>0</difficult>
		<bndbox>
			<xmin>483</xmin>
			<ymin>168</ymin>
			<xmax>539</xmax>
			<ymax>213</ymax>
		</bndbox>
	</object>
	<object>
		<name>Audi-Pict</name>
		<pose>Unspecified</pose>
		<truncated>1</truncated>
		<difficult>0</difficult>
		<bndbox>
			<xmin>31</xmin>
			<ymin>250</ymin>
			<xmax>68</xmax>
			<ymax>284</ymax>
		</bndbox>
	</object>
	<object>
		<name>Audi-Pict</name>
		<pose>Unspecified</pose>
		<truncated>1</truncated>
		<difficult>0</difficult>
		<bndbox>
			<xmin>390</xmin>
			<ymin>117</ymin>
			<xmax>481</xmax>
			<ymax>189</ymax>
		</bndbox>
	</object>
</annotation>